colson/__init__.py
colson/parser.py
colson/py.typed
colson-1.0.2.dist-info/METADATA
colson-1.0.2.dist-info/WHEEL
colson-1.0.2.dist-info/licenses/LICENSE.txt
colson-1.0.2.dist-info/RECORD
